{
  "incumbent_ids": [
    3
  ],
  "rejected_config_ids": [
    1
  ],
  "incumbents_changed": 2,
  "trajectory": [
    {
      "config_ids": [
        1
      ],
      "costs": [
        100.0
      ],
      "trial": 1,
      "walltime": 15.29928731918335
    },
    {
      "config_ids": [
        3
      ],
      "costs": [
        36.333333333333336
      ],
      "trial": 3,
      "walltime": 103.72183918952942
    }
  ],
  "state": {
    "queue": [
      [
        10,
        1
      ]
    ]
  }
}